sofinco/__init__.py
sofinco/core.py
sofinco-3.0.0.dist-info/licenses/LICENSE
sofinco-syntax/INSTALL.md
sofinco-syntax/README.md
sofinco-syntax/lazyvim/lua/plugins/sofinco.lua
sofinco-syntax/lazyvim/queries/sofinco/highlights.scm
sofinco-syntax/nano/sofinco.nanorc
sofinco-syntax/sublime/Sofinco.sublime-syntax
sofinco-syntax/vim/ftdetect/sofinco.vim
sofinco-syntax/vim/syntax/sofinco.vim
sofinco-syntax/vscode/language-configuration.json
sofinco-syntax/vscode/package.json
sofinco-syntax/vscode/syntaxes/sofinco.tmLanguage.json
sofinco-3.0.0.dist-info/METADATA
sofinco-3.0.0.dist-info/WHEEL
sofinco-3.0.0.dist-info/entry_points.txt
sofinco-3.0.0.dist-info/top_level.txt
sofinco-3.0.0.dist-info/RECORD
