Metadata-Version: 2.4
Name: sofinco
Version: 3.0.0
Summary: Bahasa Pemrograman Sofinco - Sintaks Bahasa Bugis-Makassar Berbasis Python
Author-email: levouinse <xiyonders@gmail.com>
Project-URL: Homepage, https://github.com/levouinse/sofinco-language
Project-URL: Repository, https://github.com/levouinse/sofinco-language
Project-URL: Documentation, https://github.com/levouinse/sofinco-language/wiki
Project-URL: Issues, https://github.com/levouinse/sofinco-language/issues
Keywords: sofinco,bahasa pemrograman,bahasa bugis,bahasa makassar,bugis-makassar,python
Classifier: Programming Language :: Python :: 3
Classifier: License :: OSI Approved :: MIT License
Classifier: Operating System :: OS Independent
Classifier: Intended Audience :: Developers
Classifier: Intended Audience :: Education
Classifier: Topic :: Software Development :: Interpreters
Classifier: Topic :: Education
Requires-Python: >=3.8
License-File: LICENSE
Dynamic: license-file
